{"type": "bundle", "id": "bundle--b8ab29f1-fdcd-46cf-8f04-3da784291e22", "objects": [{"type": "identity", "spec_version": "2.1", "id": "identity--fe3e9919-5ccc-5219-855b-0fb8de9ece65", "created": "2025-03-25T04:55:20.000Z", "modified": "2025-03-25T04:55:20.000Z", "name": "mallikarjunfp", "identity_class": "individual", "contact_information": "https://x.com/mallikarjunfp"}, {"type": "identity", "spec_version": "2.1", "id": "identity--88e1b21a-7b5c-5691-a6da-df79257e75c8", "created": "2025-03-25T04:55:20.000Z", "modified": "2025-03-25T04:55:20.000Z", "name": "PaduckLee", "identity_class": "individual", "contact_information": "https://x.com/PaduckLee"}, {"type": "identity", "spec_version": "2.1", "id": "identity--118bc2c8-d12a-58ad-af6d-c0ef537cc54b", "created": "2025-03-25T04:55:20.000Z", "modified": "2025-03-25T04:55:20.000Z", "name": "harugasumi", "identity_class": "individual", "contact_information": "https://x.com/harugasumi"}, {"type": "identity", "spec_version": "2.1", "id": "identity--38c8d105-74d8-540b-9223-c414a3944983", "created": "2025-03-25T04:55:20.000Z", "modified": "2025-03-25T04:55:20.000Z", "name": "drb_ra", "identity_class": "individual", "contact_information": "https://x.com/drb_ra"}, {"type": "identity", "spec_version": "2.1", "id": "identity--3680975d-79fc-510a-8b98-750ca020d93e", "created": "2025-03-25T04:55:20.000Z", "modified": "2025-03-25T04:55:20.000Z", "name": "romonlyht", "identity_class": "individual", "contact_information": "https://x.com/romonlyht"}, {"type": "identity", "spec_version": "2.1", "id": "identity--56df3021-baa0-55ba-9c06-1ff5ca83cb55", "created": "2025-03-25T04:55:20.000Z", "modified": "2025-03-25T04:55:20.000Z", "name": "catnap707", "identity_class": "individual", "contact_information": "https://x.com/catnap707"}, {"type": "identity", "spec_version": "2.1", "id": "identity--ed79cf52-2991-5d8e-b7eb-5bc9d3577885", "created": "2025-03-25T04:55:20.000Z", "modified": "2025-03-25T04:55:20.000Z", "name": "ShanHolo", "identity_class": "individual", "contact_information": "https://x.com/ShanHolo"}, {"type": "identity", "spec_version": "2.1", "id": "identity--c2d9f1ff-0792-5fce-9fd5-7b5e45ec5e5d", "created": "2025-03-25T04:55:20.000Z", "modified": "2025-03-25T04:55:20.000Z", "name": "ReBensk", "identity_class": "individual", "contact_information": "https://x.com/ReBensk"}, {"type": "identity", "spec_version": "2.1", "id": "identity--ea20bd24-c963-5a3e-924d-fca9740f3c87", "created": "2025-03-25T04:55:20.000Z", "modified": "2025-03-25T04:55:20.000Z", "name": "sicehice", "identity_class": "individual", "contact_information": "https://x.com/sicehice"}, {"type": "identity", "spec_version": "2.1", "id": "identity--8a7caf0c-f1e7-5c5c-8a42-836079f9e47b", "created": "2025-03-25T04:55:20.000Z", "modified": "2025-03-25T04:55:20.000Z", "name": "suyog41", "identity_class": "individual", "contact_information": "https://x.com/suyog41"}, {"type": "identity", "spec_version": "2.1", "id": "identity--ddd06ac5-3673-58a8-a979-6e89f953bb80", "created": "2025-03-25T04:55:20.000Z", "modified": "2025-03-25T04:55:20.000Z", "name": "petikvx", "identity_class": "individual", "contact_information": "https://x.com/petikvx"}, {"type": "indicator", "spec_version": "2.1", "id": "indicator--be7526e9-2605-5015-b2c6-a8ad72fefde7", "created_by_ref": "identity--56df3021-baa0-55ba-9c06-1ff5ca83cb55", "created": "2025-02-22T00:05:27.000Z", "modified": "2025-02-22T00:05:27.000Z", "pattern": "[url:value = 'http://e-orico-card.shop']", "pattern_type": "stix", "pattern_version": "2.1", "valid_from": "2025-03-25T04:55:20Z", "labels": ["#phishing"], "external_references": [{"source_name": "x.com", "url": "https://x.com/catnap707/status/1893089686731792764"}]}, {"type": "indicator", "spec_version": "2.1", "id": "indicator--e125080d-4ec3-54f9-b870-20de413500a7", "created_by_ref": "identity--56df3021-baa0-55ba-9c06-1ff5ca83cb55", "created": "2025-02-22T00:05:27.000Z", "modified": "2025-02-22T00:05:27.000Z", "pattern": "[url:value = 'http://move-orico-itco.shop']", "pattern_type": "stix", "pattern_version": "2.1", "valid_from": "2025-03-25T04:55:20Z", "labels": ["#phishing"], "external_references": [{"source_name": "x.com", "url": "https://x.com/catnap707/status/1893089686731792764"}]}, {"type": "indicator", "spec_version": "2.1", "id": "indicator--608fde67-2c5e-591f-9a58-bec4232a26d2", "created_by_ref": "identity--56df3021-baa0-55ba-9c06-1ff5ca83cb55", "created": "2025-02-22T00:05:27.000Z", "modified": "2025-02-22T00:05:27.000Z", "pattern": "[url:value = 'http://movee-orico.shop']", "pattern_type": "stix", "pattern_version": "2.1", "valid_from": "2025-03-25T04:55:20Z", "labels": ["#phishing"], "external_references": [{"source_name": "x.com", "url": "https://x.com/catnap707/status/1893089686731792764"}]}, {"type": "indicator", "spec_version": "2.1", "id": "indicator--ea64560b-eea5-5d7e-9259-a3ebf86427df", "created_by_ref": "identity--56df3021-baa0-55ba-9c06-1ff5ca83cb55", "created": "2025-02-22T00:05:27.000Z", "modified": "2025-02-22T00:05:27.000Z", "pattern": "[url:value = 'http://myorico-cardsco.shop']", "pattern_type": "stix", "pattern_version": "2.1", "valid_from": "2025-03-25T04:55:20Z", "labels": ["#phishing"], "external_references": [{"source_name": "x.com", "url": "https://x.com/catnap707/status/1893089686731792764"}]}, {"type": "indicator", "spec_version": "2.1", "id": "indicator--7578f152-674e-534b-88c7-6fe4c921610f", "created_by_ref": "identity--56df3021-baa0-55ba-9c06-1ff5ca83cb55", "created": "2025-02-22T00:09:35.000Z", "modified": "2025-02-22T00:09:35.000Z", "pattern": "[url:value = 'http://orico-partyard.olkiw.cn/eorico/login/']", "pattern_type": "stix", "pattern_version": "2.1", "valid_from": "2025-03-25T04:55:20Z", "labels": ["#phishing"], "external_references": [{"source_name": "x.com", "url": "https://x.com/catnap707/status/1893090723630928176"}]}, {"type": "indicator", "spec_version": "2.1", "id": "indicator--63788633-31e1-52fe-8ea0-480a97b5b70f", "created_by_ref": "identity--56df3021-baa0-55ba-9c06-1ff5ca83cb55", "created": "2025-02-22T00:09:35.000Z", "modified": "2025-02-22T00:09:35.000Z", "pattern": "[url:value = 'http://orico-rapaciid.xqyrr.cn/eorico/login/']", "pattern_type": "stix", "pattern_version": "2.1", "valid_from": "2025-03-25T04:55:20Z", "labels": ["#phishing"], "external_references": [{"source_name": "x.com", "url": "https://x.com/catnap707/status/1893090723630928176"}]}, {"type": "indicator", "spec_version": "2.1", "id": "indicator--8b4dccd4-f746-5f6a-8709-3846b96d5ac5", "created_by_ref": "identity--118bc2c8-d12a-58ad-af6d-c0ef537cc54b", "created": "2025-02-22T00:26:06.000Z", "modified": "2025-02-22T00:26:06.000Z", "pattern": "[url:value = 'https://www.accounty-kagoya.com']", "pattern_type": "stix", "pattern_version": "2.1", "valid_from": "2025-03-25T04:55:20Z", "labels": ["#phishing"], "external_references": [{"source_name": "x.com", "url": "https://x.com/harugasumi/status/1893094883881295947"}]}, {"type": "indicator", "spec_version": "2.1", "id": "indicator--1df4bfa1-302c-5cf9-9955-12b28efd9ba6", "created_by_ref": "identity--56df3021-baa0-55ba-9c06-1ff5ca83cb55", "created": "2025-02-22T00:26:50.000Z", "modified": "2025-02-22T00:26:50.000Z", "pattern": "[url:value = 'http://coolcc.appstorepay.travel.in']", "pattern_type": "stix", "pattern_version": "2.1", "valid_from": "2025-03-25T04:55:20Z", "labels": ["#phishing"], "external_references": [{"source_name": "x.com", "url": "https://x.com/catnap707/status/1893095068359352403"}]}, {"type": "indicator", "spec_version": "2.1", "id": "indicator--37dd92b3-4054-5a44-b02f-1ff7b437ad4c", "created_by_ref": "identity--56df3021-baa0-55ba-9c06-1ff5ca83cb55", "created": "2025-02-22T00:26:50.000Z", "modified": "2025-02-22T00:26:50.000Z", "pattern": "[url:value = 'http://coolcc.appstorepay.pg.in']", "pattern_type": "stix", "pattern_version": "2.1", "valid_from": "2025-03-25T04:55:20Z", "labels": ["#phishing"], "external_references": [{"source_name": "x.com", "url": "https://x.com/catnap707/status/1893095068359352403"}]}, {"type": "indicator", "spec_version": "2.1", "id": "indicator--d9c9e972-e817-59ac-bcaf-cfa6b7b25a51", "created_by_ref": "identity--56df3021-baa0-55ba-9c06-1ff5ca83cb55", "created": "2025-02-22T00:26:50.000Z", "modified": "2025-02-22T00:26:50.000Z", "pattern": "[url:value = 'http://coolcc.appstorepay.io.in']", "pattern_type": "stix", "pattern_version": "2.1", "valid_from": "2025-03-25T04:55:20Z", "labels": ["#phishing"], "external_references": [{"source_name": "x.com", "url": "https://x.com/catnap707/status/1893095068359352403"}]}, {"type": "indicator", "spec_version": "2.1", "id": "indicator--713f11be-c737-591e-b82e-a099aada8bc0", "created_by_ref": "identity--56df3021-baa0-55ba-9c06-1ff5ca83cb55", "created": "2025-02-22T00:26:50.000Z", "modified": "2025-02-22T00:26:50.000Z", "pattern": "[url:value = 'http://coolcc.appstorepay.ind.in']", "pattern_type": "stix", "pattern_version": "2.1", "valid_from": "2025-03-25T04:55:20Z", "labels": ["#phishing"], "external_references": [{"source_name": "x.com", "url": "https://x.com/catnap707/status/1893095068359352403"}]}, {"type": "indicator", "spec_version": "2.1", "id": "indicator--baab4e76-e03b-52bf-9331-0044ca49bcc7", "created_by_ref": "identity--56df3021-baa0-55ba-9c06-1ff5ca83cb55", "created": "2025-02-22T00:26:50.000Z", "modified": "2025-02-22T00:26:50.000Z", "pattern": "[url:value = 'http://coolcc.appstorepay.gujarat.in']", "pattern_type": "stix", "pattern_version": "2.1", "valid_from": "2025-03-25T04:55:20Z", "labels": ["#phishing"], "external_references": [{"source_name": "x.com", "url": "https://x.com/catnap707/status/1893095068359352403"}]}, {"type": "indicator", "spec_version": "2.1", "id": "indicator--564b8528-930f-5f65-9a37-00214d3fb4e2", "created_by_ref": "identity--118bc2c8-d12a-58ad-af6d-c0ef537cc54b", "created": "2025-02-22T00:32:16.000Z", "modified": "2025-02-22T00:32:16.000Z", "pattern": "[url:value = 'https://onamae-vps.admnz-okncz.net']", "pattern_type": "stix", "pattern_version": "2.1", "valid_from": "2025-03-25T04:55:20Z", "labels": ["#phishing"], "external_references": [{"source_name": "x.com", "url": "https://x.com/harugasumi/status/1893096435647947001"}]}, {"type": "indicator", "spec_version": "2.1", "id": "indicator--d2074835-ea77-5bc1-a9c1-6665c81ee1bd", "created_by_ref": "identity--56df3021-baa0-55ba-9c06-1ff5ca83cb55", "created": "2025-02-22T00:41:06.000Z", "modified": "2025-02-22T00:41:06.000Z", "pattern": "[url:value = 'http://ycfyzc.com']", "pattern_type": "stix", "pattern_version": "2.1", "valid_from": "2025-03-25T04:55:20Z", "labels": ["#phishing"], "external_references": [{"source_name": "x.com", "url": "https://x.com/catnap707/status/1893098657517633787"}]}, {"type": "indicator", "spec_version": "2.1", "id": "indicator--c8cc6329-a49d-5155-b448-e6b737f4d208", "created_by_ref": "identity--56df3021-baa0-55ba-9c06-1ff5ca83cb55", "created": "2025-02-22T00:41:06.000Z", "modified": "2025-02-22T00:41:06.000Z", "pattern": "[url:value = 'http://zjgwbaoan.com']", "pattern_type": "stix", "pattern_version": "2.1", "valid_from": "2025-03-25T04:55:20Z", "labels": ["#phishing"], "external_references": [{"source_name": "x.com", "url": "https://x.com/catnap707/status/1893098657517633787"}]}, {"type": "indicator", "spec_version": "2.1", "id": "indicator--6f014512-1c29-5491-935e-ee4dd8c689e1", "created_by_ref": "identity--56df3021-baa0-55ba-9c06-1ff5ca83cb55", "created": "2025-02-22T00:41:06.000Z", "modified": "2025-02-22T00:41:06.000Z", "pattern": "[url:value = 'http://zhonglongedu.com']", "pattern_type": "stix", "pattern_version": "2.1", "valid_from": "2025-03-25T04:55:20Z", "labels": ["#phishing"], "external_references": [{"source_name": "x.com", "url": "https://x.com/catnap707/status/1893098657517633787"}]}, {"type": "indicator", "spec_version": "2.1", "id": "indicator--992b9e09-1b9a-50c5-9ef0-25ceeb891844", "created_by_ref": "identity--56df3021-baa0-55ba-9c06-1ff5ca83cb55", "created": "2025-02-22T00:41:06.000Z", "modified": "2025-02-22T00:41:06.000Z", "pattern": "[url:value = 'http://tjnlccxs.com']", "pattern_type": "stix", "pattern_version": "2.1", "valid_from": "2025-03-25T04:55:20Z", "labels": ["#phishing"], "external_references": [{"source_name": "x.com", "url": "https://x.com/catnap707/status/1893098657517633787"}]}, {"type": "indicator", "spec_version": "2.1", "id": "indicator--3648dc7f-fcf7-5e34-8790-cae5ca9e65bd", "created_by_ref": "identity--56df3021-baa0-55ba-9c06-1ff5ca83cb55", "created": "2025-02-22T00:41:06.000Z", "modified": "2025-02-22T00:41:06.000Z", "pattern": "[url:value = 'http://xaxfzs.com']", "pattern_type": "stix", "pattern_version": "2.1", "valid_from": "2025-03-25T04:55:20Z", "labels": ["#phishing"], "external_references": [{"source_name": "x.com", "url": "https://x.com/catnap707/status/1893098657517633787"}]}, {"type": "indicator", "spec_version": "2.1", "id": "indicator--32a63b72-4009-5347-b69e-939557819930", "created_by_ref": "identity--56df3021-baa0-55ba-9c06-1ff5ca83cb55", "created": "2025-02-22T00:41:06.000Z", "modified": "2025-02-22T00:41:06.000Z", "pattern": "[url:value = 'http://wwwgzth.com']", "pattern_type": "stix", "pattern_version": "2.1", "valid_from": "2025-03-25T04:55:20Z", "labels": ["#phishing"], "external_references": [{"source_name": "x.com", "url": "https://x.com/catnap707/status/1893098657517633787"}]}, {"type": "indicator", "spec_version": "2.1", "id": "indicator--e1f53f1a-9f45-5f6a-84f2-37f08673d974", "created_by_ref": "identity--56df3021-baa0-55ba-9c06-1ff5ca83cb55", "created": "2025-02-22T00:41:06.000Z", "modified": "2025-02-22T00:41:06.000Z", "pattern": "[url:value = 'http://xnygdl.com']", "pattern_type": "stix", "pattern_version": "2.1", "valid_from": "2025-03-25T04:55:20Z", "labels": ["#phishing"], "external_references": [{"source_name": "x.com", "url": "https://x.com/catnap707/status/1893098657517633787"}]}, {"type": "indicator", "spec_version": "2.1", "id": "indicator--fdc654a0-ca86-50af-a584-e6fffc086286", "created_by_ref": "identity--56df3021-baa0-55ba-9c06-1ff5ca83cb55", "created": "2025-02-22T00:41:06.000Z", "modified": "2025-02-22T00:41:06.000Z", "pattern": "[url:value = 'http://yzyclass.com']", "pattern_type": "stix", "pattern_version": "2.1", "valid_from": "2025-03-25T04:55:20Z", "labels": ["#phishing"], "external_references": [{"source_name": "x.com", "url": "https://x.com/catnap707/status/1893098657517633787"}]}, {"type": "indicator", "spec_version": "2.1", "id": "indicator--46ea2700-e9a3-5585-b386-521af54c94fd", "created_by_ref": "identity--56df3021-baa0-55ba-9c06-1ff5ca83cb55", "created": "2025-02-22T00:41:06.000Z", "modified": "2025-02-22T00:41:06.000Z", "pattern": "[url:value = 'http://jsywpg.com']", "pattern_type": "stix", "pattern_version": "2.1", "valid_from": "2025-03-25T04:55:20Z", "labels": ["#phishing"], "external_references": [{"source_name": "x.com", "url": "https://x.com/catnap707/status/1893098657517633787"}]}, {"type": "indicator", "spec_version": "2.1", "id": "indicator--d196c15b-6ceb-52a5-892a-d49e4c45a66d", "created_by_ref": "identity--56df3021-baa0-55ba-9c06-1ff5ca83cb55", "created": "2025-02-22T00:41:06.000Z", "modified": "2025-02-22T00:41:06.000Z", "pattern": "[url:value = 'http://jxhg888.com']", "pattern_type": "stix", "pattern_version": "2.1", "valid_from": "2025-03-25T04:55:20Z", "labels": ["#phishing"], "external_references": [{"source_name": "x.com", "url": "https://x.com/catnap707/status/1893098657517633787"}]}, {"type": "indicator", "spec_version": "2.1", "id": "indicator--15ec2fab-b08c-589f-8648-beec7f18fb25", "created_by_ref": "identity--56df3021-baa0-55ba-9c06-1ff5ca83cb55", "created": "2025-02-22T00:41:06.000Z", "modified": "2025-02-22T00:41:06.000Z", "pattern": "[url:value = 'http://shangbiaozhinan.com']", "pattern_type": "stix", "pattern_version": "2.1", "valid_from": "2025-03-25T04:55:20Z", "labels": ["#phishing"], "external_references": [{"source_name": "x.com", "url": "https://x.com/catnap707/status/1893098657517633787"}]}, {"type": "indicator", "spec_version": "2.1", "id": "indicator--8b5c997c-46c4-5b5c-9f5c-1c1513352cc6", "created_by_ref": "identity--56df3021-baa0-55ba-9c06-1ff5ca83cb55", "created": "2025-02-22T00:41:06.000Z", "modified": "2025-02-22T00:41:06.000Z", "pattern": "[url:value = 'http://ktshomeservices.com']", "pattern_type": "stix", "pattern_version": "2.1", "valid_from": "2025-03-25T04:55:20Z", "labels": ["#phishing"], "external_references": [{"source_name": "x.com", "url": "https://x.com/catnap707/status/1893098657517633787"}]}, {"type": "indicator", "spec_version": "2.1", "id": "indicator--d8dad826-3408-52da-80da-9efb4c2860dd", "created_by_ref": "identity--56df3021-baa0-55ba-9c06-1ff5ca83cb55", "created": "2025-02-22T01:29:06.000Z", "modified": "2025-02-22T01:29:06.000Z", "pattern": "[ipv4-addr:value = '104.21.16.166']", "pattern_type": "stix", "pattern_version": "2.1", "valid_from": "2025-03-25T04:55:20Z", "labels": ["#phishing"], "external_references": [{"source_name": "x.com", "url": "https://x.com/catnap707/status/1893110734525210644"}]}, {"type": "indicator", "spec_version": "2.1", "id": "indicator--7f7bac2c-cb86-58f2-917d-c590108d4ff7", "created_by_ref": "identity--56df3021-baa0-55ba-9c06-1ff5ca83cb55", "created": "2025-02-22T01:29:06.000Z", "modified": "2025-02-22T01:29:06.000Z", "pattern": "[ipv4-addr:value = '172.67.214.220']", "pattern_type": "stix", "pattern_version": "2.1", "valid_from": "2025-03-25T04:55:20Z", "labels": ["#phishing"], "external_references": [{"source_name": "x.com", "url": "https://x.com/catnap707/status/1893110734525210644"}]}, {"type": "indicator", "spec_version": "2.1", "id": "indicator--1b45b67b-2d71-5359-a635-ff32bc8835b6", "created_by_ref": "identity--38c8d105-74d8-540b-9223-c414a3944983", "created": "2025-02-22T06:46:00.000Z", "modified": "2025-02-22T06:46:00.000Z", "pattern": "[ipv4-addr:value = '185.193.126.20']", "pattern_type": "stix", "pattern_version": "2.1", "valid_from": "2025-03-25T04:55:20Z", "labels": ["#C2", "#Havoc"], "external_references": [{"source_name": "x.com", "url": "https://x.com/drb_ra/status/1893190487839846409"}]}, {"type": "indicator", "spec_version": "2.1", "id": "indicator--57b6037b-6bfa-55d4-abd0-8ac1bda938d2", "created_by_ref": "identity--38c8d105-74d8-540b-9223-c414a3944983", "created": "2025-02-22T06:46:04.000Z", "modified": "2025-02-22T06:46:04.000Z", "pattern": "[ipv4-addr:value = '91.200.101.43']", "pattern_type": "stix", "pattern_version": "2.1", "valid_from": "2025-03-25T04:55:20Z", "labels": ["#C2", "#Havoc"], "external_references": [{"source_name": "x.com", "url": "https://x.com/drb_ra/status/1893190503555822078"}]}, {"type": "indicator", "spec_version": "2.1", "id": "indicator--cd7bb4fa-39b0-5904-b653-8491f8ff097a", "created_by_ref": "identity--38c8d105-74d8-540b-9223-c414a3944983", "created": "2025-02-22T06:46:08.000Z", "modified": "2025-02-22T06:46:08.000Z", "pattern": "[ipv4-addr:value = '196.251.118.109']", "pattern_type": "stix", "pattern_version": "2.1", "valid_from": "2025-03-25T04:55:20Z", "labels": ["#C2", "#Havoc"], "external_references": [{"source_name": "x.com", "url": "https://x.com/drb_ra/status/1893190519284486637"}]}, {"type": "indicator", "spec_version": "2.1", "id": "indicator--2771bb80-07fb-5dc1-a6e8-f5be10228087", "created_by_ref": "identity--38c8d105-74d8-540b-9223-c414a3944983", "created": "2025-02-22T06:46:28.000Z", "modified": "2025-02-22T06:46:28.000Z", "pattern": "[ipv4-addr:value = '138.197.25.162']", "pattern_type": "stix", "pattern_version": "2.1", "valid_from": "2025-03-25T04:55:20Z", "labels": ["#C2", "#Evilginx", "#EvilGoPhish"], "external_references": [{"source_name": "x.com", "url": "https://x.com/drb_ra/status/1893190604978286793"}]}, {"type": "indicator", "spec_version": "2.1", "id": "indicator--e5572ed9-a9af-5d04-8046-abfae45bcc5b", "created_by_ref": "identity--38c8d105-74d8-540b-9223-c414a3944983", "created": "2025-02-22T06:46:31.000Z", "modified": "2025-02-22T06:46:31.000Z", "pattern": "[ipv4-addr:value = '109.120.137.86']", "pattern_type": "stix", "pattern_version": "2.1", "valid_from": "2025-03-25T04:55:20Z", "labels": ["#Pegasus", "#C2", "#Hookbot"], "external_references": [{"source_name": "x.com", "url": "https://x.com/drb_ra/status/1893190617414406356"}]}, {"type": "indicator", "spec_version": "2.1", "id": "indicator--d1b3cf2e-523a-5529-82a8-78b136b090b1", "created_by_ref": "identity--38c8d105-74d8-540b-9223-c414a3944983", "created": "2025-02-22T06:46:41.000Z", "modified": "2025-02-22T06:46:41.000Z", "pattern": "[ipv4-addr:value = '200.195.146.57']", "pattern_type": "stix", "pattern_version": "2.1", "valid_from": "2025-03-25T04:55:20Z", "labels": ["#Interactsh", "#C2"], "external_references": [{"source_name": "x.com", "url": "https://x.com/drb_ra/status/1893190660741558285"}]}, {"type": "indicator", "spec_version": "2.1", "id": "indicator--274abb6c-0701-5552-920e-7ab1f725c4d9", "created_by_ref": "identity--38c8d105-74d8-540b-9223-c414a3944983", "created": "2025-02-22T06:46:52.000Z", "modified": "2025-02-22T06:46:52.000Z", "pattern": "[ipv4-addr:value = '193.163.203.62']", "pattern_type": "stix", "pattern_version": "2.1", "valid_from": "2025-03-25T04:55:20Z", "labels": ["#C2", "#Mythic"], "external_references": [{"source_name": "x.com", "url": "https://x.com/drb_ra/status/1893190703066313140"}]}, {"type": "indicator", "spec_version": "2.1", "id": "indicator--7a1aab9a-a214-595f-8690-c2ce913af8bd", "created_by_ref": "identity--38c8d105-74d8-540b-9223-c414a3944983", "created": "2025-02-22T06:46:54.000Z", "modified": "2025-02-22T06:46:54.000Z", "pattern": "[ipv4-addr:value = '209.97.188.52']", "pattern_type": "stix", "pattern_version": "2.1", "valid_from": "2025-03-25T04:55:20Z", "labels": ["#Interactsh", "#C2"], "external_references": [{"source_name": "x.com", "url": "https://x.com/drb_ra/status/1893190714592317645"}]}, {"type": "indicator", "spec_version": "2.1", "id": "indicator--a2c6b084-1a69-5bca-9e8f-39a6fc9de388", "created_by_ref": "identity--38c8d105-74d8-540b-9223-c414a3944983", "created": "2025-02-22T06:46:59.000Z", "modified": "2025-02-22T06:46:59.000Z", "pattern": "[ipv4-addr:value = '85.239.245.157']", "pattern_type": "stix", "pattern_version": "2.1", "valid_from": "2025-03-25T04:55:20Z", "labels": ["#AsyncRAT", "#C2"], "external_references": [{"source_name": "x.com", "url": "https://x.com/drb_ra/status/1893190735614095574"}]}, {"type": "indicator", "spec_version": "2.1", "id": "indicator--2c46eb12-90eb-5520-9ce2-d9b907cf2d53", "created_by_ref": "identity--38c8d105-74d8-540b-9223-c414a3944983", "created": "2025-02-22T06:47:03.000Z", "modified": "2025-02-22T06:47:03.000Z", "pattern": "[ipv4-addr:value = '163.5.112.109']", "pattern_type": "stix", "pattern_version": "2.1", "valid_from": "2025-03-25T04:55:20Z", "labels": ["#AsyncRAT", "#C2"], "external_references": [{"source_name": "x.com", "url": "https://x.com/drb_ra/status/1893190749371441310"}]}, {"type": "indicator", "spec_version": "2.1", "id": "indicator--544c8ece-6e1a-586e-ac6f-f8c9dacd931a", "created_by_ref": "identity--38c8d105-74d8-540b-9223-c414a3944983", "created": "2025-02-22T06:47:06.000Z", "modified": "2025-02-22T06:47:06.000Z", "pattern": "[ipv4-addr:value = '193.26.115.69']", "pattern_type": "stix", "pattern_version": "2.1", "valid_from": "2025-03-25T04:55:20Z", "labels": ["#AsyncRAT", "#C2"], "external_references": [{"source_name": "x.com", "url": "https://x.com/drb_ra/status/1893190762570924111"}]}, {"type": "indicator", "spec_version": "2.1", "id": "indicator--34bbcb74-e361-5e73-85a1-2c51b2cd443c", "created_by_ref": "identity--38c8d105-74d8-540b-9223-c414a3944983", "created": "2025-02-22T06:47:08.000Z", "modified": "2025-02-22T06:47:08.000Z", "pattern": "[ipv4-addr:value = '38.18.228.187']", "pattern_type": "stix", "pattern_version": "2.1", "valid_from": "2025-03-25T04:55:20Z", "labels": ["#AsyncRAT", "#C2"], "external_references": [{"source_name": "x.com", "url": "https://x.com/drb_ra/status/1893190771592794153"}]}, {"type": "indicator", "spec_version": "2.1", "id": "indicator--ecbc0d5e-4d4e-5c1f-af2d-0fc7bc5a19c8", "created_by_ref": "identity--38c8d105-74d8-540b-9223-c414a3944983", "created": "2025-02-22T06:47:16.000Z", "modified": "2025-02-22T06:47:16.000Z", "pattern": "[ipv4-addr:value = '18.220.190.184']", "pattern_type": "stix", "pattern_version": "2.1", "valid_from": "2025-03-25T04:55:20Z", "labels": ["#C2", "#NetSupportRAT"], "external_references": [{"source_name": "x.com", "url": "https://x.com/drb_ra/status/1893190806015496585"}]}, {"type": "indicator", "spec_version": "2.1", "id": "indicator--fd7b6014-f553-5bf3-90fa-d27879fb0baa", "created_by_ref": "identity--38c8d105-74d8-540b-9223-c414a3944983", "created": "2025-02-22T06:48:55.000Z", "modified": "2025-02-22T06:48:55.000Z", "pattern": "[ipv4-addr:value = '95.164.113.238']", "pattern_type": "stix", "pattern_version": "2.1", "valid_from": "2025-03-25T04:55:20Z", "labels": ["#C2"], "external_references": [{"source_name": "x.com", "url": "https://x.com/drb_ra/status/1893191219552887264"}]}, {"type": "indicator", "spec_version": "2.1", "id": "indicator--a40c15e1-66c4-5340-a623-dc5de0c01d0d", "created_by_ref": "identity--38c8d105-74d8-540b-9223-c414a3944983", "created": "2025-02-22T06:48:59.000Z", "modified": "2025-02-22T06:48:59.000Z", "pattern": "[ipv4-addr:value = '173.249.39.212']", "pattern_type": "stix", "pattern_version": "2.1", "valid_from": "2025-03-25T04:55:20Z", "labels": ["#Remcos", "#C2"], "external_references": [{"source_name": "x.com", "url": "https://x.com/drb_ra/status/1893191236233687506"}]}, {"type": "indicator", "spec_version": "2.1", "id": "indicator--02cd4197-36b8-5f1a-9f49-0c24b0ea34c9", "created_by_ref": "identity--38c8d105-74d8-540b-9223-c414a3944983", "created": "2025-02-22T06:49:02.000Z", "modified": "2025-02-22T06:49:02.000Z", "pattern": "[ipv4-addr:value = '172.94.9.179']", "pattern_type": "stix", "pattern_version": "2.1", "valid_from": "2025-03-25T04:55:20Z", "labels": ["#Remcos", "#C2"], "external_references": [{"source_name": "x.com", "url": "https://x.com/drb_ra/status/1893191251211505820"}]}, {"type": "indicator", "spec_version": "2.1", "id": "indicator--2a3404e7-3422-5c3d-b1e8-2839002fd291", "created_by_ref": "identity--38c8d105-74d8-540b-9223-c414a3944983", "created": "2025-02-22T06:49:07.000Z", "modified": "2025-02-22T06:49:07.000Z", "pattern": "[ipv4-addr:value = '13.125.181.205']", "pattern_type": "stix", "pattern_version": "2.1", "valid_from": "2025-03-25T04:55:20Z", "labels": ["#C2", "#NetSupportRAT"], "external_references": [{"source_name": "x.com", "url": "https://x.com/drb_ra/status/1893191272032063601"}]}, {"type": "indicator", "spec_version": "2.1", "id": "indicator--8d84470a-64e7-59de-9f07-db7c4c2ce989", "created_by_ref": "identity--38c8d105-74d8-540b-9223-c414a3944983", "created": "2025-02-22T06:49:11.000Z", "modified": "2025-02-22T06:49:11.000Z", "pattern": "[ipv4-addr:value = '13.40.111.214']", "pattern_type": "stix", "pattern_version": "2.1", "valid_from": "2025-03-25T04:55:20Z", "labels": ["#C2", "#NetSupportRAT"], "external_references": [{"source_name": "x.com", "url": "https://x.com/drb_ra/status/1893191289551704230"}]}, {"type": "indicator", "spec_version": "2.1", "id": "indicator--aac5b545-3d53-5416-9278-95d4b41f915d", "created_by_ref": "identity--38c8d105-74d8-540b-9223-c414a3944983", "created": "2025-02-22T06:49:16.000Z", "modified": "2025-02-22T06:49:16.000Z", "pattern": "[ipv4-addr:value = '13.37.238.216']", "pattern_type": "stix", "pattern_version": "2.1", "valid_from": "2025-03-25T04:55:20Z", "labels": ["#C2", "#NetSupportRAT"], "external_references": [{"source_name": "x.com", "url": "https://x.com/drb_ra/status/1893191307742302447"}]}, {"type": "indicator", "spec_version": "2.1", "id": "indicator--c8983fe9-6c13-5c98-9d88-68c3ffefcef7", "created_by_ref": "identity--38c8d105-74d8-540b-9223-c414a3944983", "created": "2025-02-22T06:49:20.000Z", "modified": "2025-02-22T06:49:20.000Z", "pattern": "[ipv4-addr:value = '179.95.205.120']", "pattern_type": "stix", "pattern_version": "2.1", "valid_from": "2025-03-25T04:55:20Z", "labels": ["#C2", "#NetSupportRAT"], "external_references": [{"source_name": "x.com", "url": "https://x.com/drb_ra/status/1893191326478254556"}]}, {"type": "indicator", "spec_version": "2.1", "id": "indicator--21bef1a8-2a3c-5102-b405-2bfc20574177", "created_by_ref": "identity--38c8d105-74d8-540b-9223-c414a3944983", "created": "2025-02-22T10:14:18.000Z", "modified": "2025-02-22T10:14:18.000Z", "pattern": "[ipv4-addr:value = '45.76.136.228']", "pattern_type": "stix", "pattern_version": "2.1", "valid_from": "2025-03-25T04:55:20Z", "labels": ["#C2", "#CobaltStrike"], "external_references": [{"source_name": "x.com", "url": "https://x.com/drb_ra/status/1893242907299053918"}]}, {"type": "indicator", "spec_version": "2.1", "id": "indicator--05544042-2be2-53c6-81b9-345dc2940aaa", "created_by_ref": "identity--38c8d105-74d8-540b-9223-c414a3944983", "created": "2025-02-22T10:14:23.000Z", "modified": "2025-02-22T10:14:23.000Z", "pattern": "[ipv4-addr:value = '16.62.96.40']", "pattern_type": "stix", "pattern_version": "2.1", "valid_from": "2025-03-25T04:55:20Z", "labels": ["#C2", "#CobaltStrike"], "external_references": [{"source_name": "x.com", "url": "https://x.com/drb_ra/status/1893242926945169751"}]}, {"type": "indicator", "spec_version": "2.1", "id": "indicator--45e6f145-848b-513b-bc26-aa62fd6c4e8f", "created_by_ref": "identity--38c8d105-74d8-540b-9223-c414a3944983", "created": "2025-02-22T10:14:32.000Z", "modified": "2025-02-22T10:14:32.000Z", "pattern": "[ipv4-addr:value = '154.92.14.41']", "pattern_type": "stix", "pattern_version": "2.1", "valid_from": "2025-03-25T04:55:20Z", "labels": ["#C2", "#CobaltStrike"], "external_references": [{"source_name": "x.com", "url": "https://x.com/drb_ra/status/1893242966602350688"}]}, {"type": "indicator", "spec_version": "2.1", "id": "indicator--d6b62c05-b7c1-565b-be66-d9bedf0fdd9f", "created_by_ref": "identity--56df3021-baa0-55ba-9c06-1ff5ca83cb55", "created": "2025-02-22T00:05:27.000Z", "modified": "2025-02-22T00:05:27.000Z", "pattern": "[domain-name:value = 'e-orico-card.shop']", "pattern_type": "stix", "pattern_version": "2.1", "valid_from": "2025-03-25T04:55:20Z", "labels": ["#phishing"], "external_references": [{"source_name": "x.com", "url": "https://x.com/catnap707/status/1893089686731792764"}]}, {"type": "indicator", "spec_version": "2.1", "id": "indicator--e11716e6-e4a5-5883-abdd-2dc41735c758", "created_by_ref": "identity--56df3021-baa0-55ba-9c06-1ff5ca83cb55", "created": "2025-02-22T00:05:27.000Z", "modified": "2025-02-22T00:05:27.000Z", "pattern": "[domain-name:value = 'move-orico-itco.shop']", "pattern_type": "stix", "pattern_version": "2.1", "valid_from": "2025-03-25T04:55:20Z", "labels": ["#phishing"], "external_references": [{"source_name": "x.com", "url": "https://x.com/catnap707/status/1893089686731792764"}]}, {"type": "indicator", "spec_version": "2.1", "id": "indicator--3ea76888-8606-5e7e-8872-bf666529747a", "created_by_ref": "identity--56df3021-baa0-55ba-9c06-1ff5ca83cb55", "created": "2025-02-22T00:05:27.000Z", "modified": "2025-02-22T00:05:27.000Z", "pattern": "[domain-name:value = 'movee-orico.shop']", "pattern_type": "stix", "pattern_version": "2.1", "valid_from": "2025-03-25T04:55:20Z", "labels": ["#phishing"], "external_references": [{"source_name": "x.com", "url": "https://x.com/catnap707/status/1893089686731792764"}]}, {"type": "indicator", "spec_version": "2.1", "id": "indicator--153c4973-943a-584c-8dc4-ec2507cafe1e", "created_by_ref": "identity--56df3021-baa0-55ba-9c06-1ff5ca83cb55", "created": "2025-02-22T00:05:27.000Z", "modified": "2025-02-22T00:05:27.000Z", "pattern": "[domain-name:value = 'myorico-cardsco.shop']", "pattern_type": "stix", "pattern_version": "2.1", "valid_from": "2025-03-25T04:55:20Z", "labels": ["#phishing"], "external_references": [{"source_name": "x.com", "url": "https://x.com/catnap707/status/1893089686731792764"}]}, {"type": "indicator", "spec_version": "2.1", "id": "indicator--45669c19-018a-520f-b220-49d0ca3b2e5f", "created_by_ref": "identity--56df3021-baa0-55ba-9c06-1ff5ca83cb55", "created": "2025-02-22T00:09:35.000Z", "modified": "2025-02-22T00:09:35.000Z", "pattern": "[domain-name:value = 'orico-partyard.olkiw.cn']", "pattern_type": "stix", "pattern_version": "2.1", "valid_from": "2025-03-25T04:55:20Z", "labels": ["#phishing"], "external_references": [{"source_name": "x.com", "url": "https://x.com/catnap707/status/1893090723630928176"}]}, {"type": "indicator", "spec_version": "2.1", "id": "indicator--06c1a762-cef8-598e-b847-0a8880154ada", "created_by_ref": "identity--56df3021-baa0-55ba-9c06-1ff5ca83cb55", "created": "2025-02-22T00:09:35.000Z", "modified": "2025-02-22T00:09:35.000Z", "pattern": "[domain-name:value = 'orico-rapaciid.xqyrr.cn']", "pattern_type": "stix", "pattern_version": "2.1", "valid_from": "2025-03-25T04:55:20Z", "labels": ["#phishing"], "external_references": [{"source_name": "x.com", "url": "https://x.com/catnap707/status/1893090723630928176"}]}, {"type": "indicator", "spec_version": "2.1", "id": "indicator--445e1dd1-f8ea-57d7-b5c7-52b5f75e07e3", "created_by_ref": "identity--118bc2c8-d12a-58ad-af6d-c0ef537cc54b", "created": "2025-02-22T00:26:06.000Z", "modified": "2025-02-22T00:26:06.000Z", "pattern": "[domain-name:value = 'accounty-kagoya.com']", "pattern_type": "stix", "pattern_version": "2.1", "valid_from": "2025-03-25T04:55:20Z", "labels": ["#phishing"], "external_references": [{"source_name": "x.com", "url": "https://x.com/harugasumi/status/1893094883881295947"}]}, {"type": "indicator", "spec_version": "2.1", "id": "indicator--bdd087ed-909b-5eed-bf26-43cc312340ce", "created_by_ref": "identity--56df3021-baa0-55ba-9c06-1ff5ca83cb55", "created": "2025-02-22T00:26:50.000Z", "modified": "2025-02-22T00:26:50.000Z", "pattern": "[domain-name:value = 'coolcc.appstorepay.pg.in']", "pattern_type": "stix", "pattern_version": "2.1", "valid_from": "2025-03-25T04:55:20Z", "labels": ["#phishing"], "external_references": [{"source_name": "x.com", "url": "https://x.com/catnap707/status/1893095068359352403"}]}, {"type": "indicator", "spec_version": "2.1", "id": "indicator--a2471108-6ab7-5bac-beb2-f6d6c5cd3913", "created_by_ref": "identity--56df3021-baa0-55ba-9c06-1ff5ca83cb55", "created": "2025-02-22T00:26:50.000Z", "modified": "2025-02-22T00:26:50.000Z", "pattern": "[domain-name:value = 'coolcc.appstorepay.travel.in']", "pattern_type": "stix", "pattern_version": "2.1", "valid_from": "2025-03-25T04:55:20Z", "labels": ["#phishing"], "external_references": [{"source_name": "x.com", "url": "https://x.com/catnap707/status/1893095068359352403"}]}, {"type": "indicator", "spec_version": "2.1", "id": "indicator--7a3d8343-f352-5834-9c67-dd14a6fd6ead", "created_by_ref": "identity--56df3021-baa0-55ba-9c06-1ff5ca83cb55", "created": "2025-02-22T00:26:50.000Z", "modified": "2025-02-22T00:26:50.000Z", "pattern": "[domain-name:value = 'coolcc.appstorepay.gujarat.in']", "pattern_type": "stix", "pattern_version": "2.1", "valid_from": "2025-03-25T04:55:20Z", "labels": ["#phishing"], "external_references": [{"source_name": "x.com", "url": "https://x.com/catnap707/status/1893095068359352403"}]}, {"type": "indicator", "spec_version": "2.1", "id": "indicator--b4d8e315-fc06-5a23-b0a6-a528f60f4b88", "created_by_ref": "identity--56df3021-baa0-55ba-9c06-1ff5ca83cb55", "created": "2025-02-22T00:26:50.000Z", "modified": "2025-02-22T00:26:50.000Z", "pattern": "[domain-name:value = 'coolcc.appstorepay.io.in']", "pattern_type": "stix", "pattern_version": "2.1", "valid_from": "2025-03-25T04:55:20Z", "labels": ["#phishing"], "external_references": [{"source_name": "x.com", "url": "https://x.com/catnap707/status/1893095068359352403"}]}, {"type": "indicator", "spec_version": "2.1", "id": "indicator--6deab9bc-b762-5b9e-9152-3cc350b33341", "created_by_ref": "identity--56df3021-baa0-55ba-9c06-1ff5ca83cb55", "created": "2025-02-22T00:26:50.000Z", "modified": "2025-02-22T00:26:50.000Z", "pattern": "[domain-name:value = 'coolcc.appstorepay.ind.in']", "pattern_type": "stix", "pattern_version": "2.1", "valid_from": "2025-03-25T04:55:20Z", "labels": ["#phishing"], "external_references": [{"source_name": "x.com", "url": "https://x.com/catnap707/status/1893095068359352403"}]}, {"type": "indicator", "spec_version": "2.1", "id": "indicator--30d31d2a-b7a0-5ac4-ae36-d3fa47932bb6", "created_by_ref": "identity--118bc2c8-d12a-58ad-af6d-c0ef537cc54b", "created": "2025-02-22T00:32:16.000Z", "modified": "2025-02-22T00:32:16.000Z", "pattern": "[domain-name:value = 'onamae-vps.admnz-okncz.net']", "pattern_type": "stix", "pattern_version": "2.1", "valid_from": "2025-03-25T04:55:20Z", "labels": ["#phishing"], "external_references": [{"source_name": "x.com", "url": "https://x.com/harugasumi/status/1893096435647947001"}]}, {"type": "indicator", "spec_version": "2.1", "id": "indicator--59648a24-fe6a-5c7f-b5b6-496b1edd9568", "created_by_ref": "identity--56df3021-baa0-55ba-9c06-1ff5ca83cb55", "created": "2025-02-22T00:41:06.000Z", "modified": "2025-02-22T00:41:06.000Z", "pattern": "[domain-name:value = 'wwwgzth.com']", "pattern_type": "stix", "pattern_version": "2.1", "valid_from": "2025-03-25T04:55:20Z", "labels": ["#phishing"], "external_references": [{"source_name": "x.com", "url": "https://x.com/catnap707/status/1893098657517633787"}]}, {"type": "indicator", "spec_version": "2.1", "id": "indicator--f906b9ed-b027-54d7-86b3-d8902bf4e60f", "created_by_ref": "identity--56df3021-baa0-55ba-9c06-1ff5ca83cb55", "created": "2025-02-22T00:41:06.000Z", "modified": "2025-02-22T00:41:06.000Z", "pattern": "[domain-name:value = 'zjgwbaoan.com']", "pattern_type": "stix", "pattern_version": "2.1", "valid_from": "2025-03-25T04:55:20Z", "labels": ["#phishing"], "external_references": [{"source_name": "x.com", "url": "https://x.com/catnap707/status/1893098657517633787"}]}, {"type": "indicator", "spec_version": "2.1", "id": "indicator--cccda5f4-e44b-5757-a536-e4b6ce4b8530", "created_by_ref": "identity--56df3021-baa0-55ba-9c06-1ff5ca83cb55", "created": "2025-02-22T00:41:06.000Z", "modified": "2025-02-22T00:41:06.000Z", "pattern": "[domain-name:value = 'yzyclass.com']", "pattern_type": "stix", "pattern_version": "2.1", "valid_from": "2025-03-25T04:55:20Z", "labels": ["#phishing"], "external_references": [{"source_name": "x.com", "url": "https://x.com/catnap707/status/1893098657517633787"}]}, {"type": "indicator", "spec_version": "2.1", "id": "indicator--dc3422e7-f6ed-5dbb-95ff-2409e9d90963", "created_by_ref": "identity--56df3021-baa0-55ba-9c06-1ff5ca83cb55", "created": "2025-02-22T00:41:06.000Z", "modified": "2025-02-22T00:41:06.000Z", "pattern": "[domain-name:value = 'xnygdl.com']", "pattern_type": "stix", "pattern_version": "2.1", "valid_from": "2025-03-25T04:55:20Z", "labels": ["#phishing"], "external_references": [{"source_name": "x.com", "url": "https://x.com/catnap707/status/1893098657517633787"}]}, {"type": "indicator", "spec_version": "2.1", "id": "indicator--77a8c9e6-74f8-5d37-9ada-20ae507039fa", "created_by_ref": "identity--56df3021-baa0-55ba-9c06-1ff5ca83cb55", "created": "2025-02-22T00:41:06.000Z", "modified": "2025-02-22T00:41:06.000Z", "pattern": "[domain-name:value = 'ycfyzc.com']", "pattern_type": "stix", "pattern_version": "2.1", "valid_from": "2025-03-25T04:55:20Z", "labels": ["#phishing"], "external_references": [{"source_name": "x.com", "url": "https://x.com/catnap707/status/1893098657517633787"}]}, {"type": "indicator", "spec_version": "2.1", "id": "indicator--59f12f31-906a-5d7e-864e-01473d061526", "created_by_ref": "identity--56df3021-baa0-55ba-9c06-1ff5ca83cb55", "created": "2025-02-22T00:41:06.000Z", "modified": "2025-02-22T00:41:06.000Z", "pattern": "[domain-name:value = 'xaxfzs.com']", "pattern_type": "stix", "pattern_version": "2.1", "valid_from": "2025-03-25T04:55:20Z", "labels": ["#phishing"], "external_references": [{"source_name": "x.com", "url": "https://x.com/catnap707/status/1893098657517633787"}]}, {"type": "indicator", "spec_version": "2.1", "id": "indicator--5d0b956d-61ee-5759-8b8d-a00ab963842b", "created_by_ref": "identity--56df3021-baa0-55ba-9c06-1ff5ca83cb55", "created": "2025-02-22T00:41:06.000Z", "modified": "2025-02-22T00:41:06.000Z", "pattern": "[domain-name:value = 'zhonglongedu.com']", "pattern_type": "stix", "pattern_version": "2.1", "valid_from": "2025-03-25T04:55:20Z", "labels": ["#phishing"], "external_references": [{"source_name": "x.com", "url": "https://x.com/catnap707/status/1893098657517633787"}]}, {"type": "indicator", "spec_version": "2.1", "id": "indicator--51aa8385-24c4-5ca5-8acb-d5ae9eba7ab6", "created_by_ref": "identity--56df3021-baa0-55ba-9c06-1ff5ca83cb55", "created": "2025-02-22T00:41:06.000Z", "modified": "2025-02-22T00:41:06.000Z", "pattern": "[domain-name:value = 'ktshomeservices.com']", "pattern_type": "stix", "pattern_version": "2.1", "valid_from": "2025-03-25T04:55:20Z", "labels": ["#phishing"], "external_references": [{"source_name": "x.com", "url": "https://x.com/catnap707/status/1893098657517633787"}]}, {"type": "indicator", "spec_version": "2.1", "id": "indicator--1aa91a1d-3fa9-5a8c-9cdb-f06ef8b6cb72", "created_by_ref": "identity--56df3021-baa0-55ba-9c06-1ff5ca83cb55", "created": "2025-02-22T00:41:06.000Z", "modified": "2025-02-22T00:41:06.000Z", "pattern": "[domain-name:value = 'tjnlccxs.com']", "pattern_type": "stix", "pattern_version": "2.1", "valid_from": "2025-03-25T04:55:20Z", "labels": ["#phishing"], "external_references": [{"source_name": "x.com", "url": "https://x.com/catnap707/status/1893098657517633787"}]}, {"type": "indicator", "spec_version": "2.1", "id": "indicator--64935e73-9730-54cd-b71c-adfff45c53cb", "created_by_ref": "identity--56df3021-baa0-55ba-9c06-1ff5ca83cb55", "created": "2025-02-22T00:41:06.000Z", "modified": "2025-02-22T00:41:06.000Z", "pattern": "[domain-name:value = 'jsywpg.com']", "pattern_type": "stix", "pattern_version": "2.1", "valid_from": "2025-03-25T04:55:20Z", "labels": ["#phishing"], "external_references": [{"source_name": "x.com", "url": "https://x.com/catnap707/status/1893098657517633787"}]}, {"type": "indicator", "spec_version": "2.1", "id": "indicator--988ac6e1-7d8a-524a-a116-f2e8459c7322", "created_by_ref": "identity--56df3021-baa0-55ba-9c06-1ff5ca83cb55", "created": "2025-02-22T00:41:06.000Z", "modified": "2025-02-22T00:41:06.000Z", "pattern": "[domain-name:value = 'jxhg888.com']", "pattern_type": "stix", "pattern_version": "2.1", "valid_from": "2025-03-25T04:55:20Z", "labels": ["#phishing"], "external_references": [{"source_name": "x.com", "url": "https://x.com/catnap707/status/1893098657517633787"}]}, {"type": "indicator", "spec_version": "2.1", "id": "indicator--203c635f-53ca-5f9f-bc47-1e221f2ea744", "created_by_ref": "identity--56df3021-baa0-55ba-9c06-1ff5ca83cb55", "created": "2025-02-22T00:41:06.000Z", "modified": "2025-02-22T00:41:06.000Z", "pattern": "[domain-name:value = 'shangbiaozhinan.com']", "pattern_type": "stix", "pattern_version": "2.1", "valid_from": "2025-03-25T04:55:20Z", "labels": ["#phishing"], "external_references": [{"source_name": "x.com", "url": "https://x.com/catnap707/status/1893098657517633787"}]}, {"type": "indicator", "spec_version": "2.1", "id": "indicator--28e43822-299c-5ac1-9d38-a201844f14e7", "created_by_ref": "identity--c2d9f1ff-0792-5fce-9fd5-7b5e45ec5e5d", "created": "2025-02-22T04:28:28.000Z", "modified": "2025-02-22T04:28:28.000Z", "pattern": "[file:hashes.MD5 = 'b70cd78e61247851f4ae7bb9be7ff3fe']", "pattern_type": "stix", "pattern_version": "2.1", "valid_from": "2025-03-25T04:55:20Z", "labels": ["#Trojan", "#Android", "#malware"], "external_references": [{"source_name": "x.com", "url": "https://x.com/ReBensk/status/1893155876145385629"}]}, {"type": "indicator", "spec_version": "2.1", "id": "indicator--6547da1c-7318-5198-8f79-c523bfb47ec1", "created_by_ref": "identity--ea20bd24-c963-5a3e-924d-fca9740f3c87", "created": "2025-02-22T16:09:34.000Z", "modified": "2025-02-22T16:09:34.000Z", "pattern": "[file:hashes.MD5 = 'b7eb8e66f765a5c0a8d0ddf3ff763c3e']", "pattern_type": "stix", "pattern_version": "2.1", "valid_from": "2025-03-25T04:55:20Z", "external_references": [{"source_name": "x.com", "url": "https://x.com/sicehice/status/1893332313401934244"}]}, {"type": "indicator", "spec_version": "2.1", "id": "indicator--00a5650d-25a6-5c52-ace4-53488ef3c136", "created_by_ref": "identity--ddd06ac5-3673-58a8-a979-6e89f953bb80", "created": "2025-02-22T20:34:29.000Z", "modified": "2025-02-22T20:34:29.000Z", "pattern": "[file:hashes.MD5 = '4023c6b64bafc1281bd8fd4c497dff96']", "pattern_type": "stix", "pattern_version": "2.1", "valid_from": "2025-03-25T04:55:20Z", "labels": ["#ransomware"], "external_references": [{"source_name": "x.com", "url": "https://x.com/petikvx/status/1893398980219875535"}]}, {"type": "indicator", "spec_version": "2.1", "id": "indicator--bf75e779-7f81-5de8-8e9f-826f4f66b812", "created_by_ref": "identity--ed79cf52-2991-5d8e-b7eb-5bc9d3577885", "created": "2025-02-23T09:36:42.000Z", "modified": "2025-02-23T09:36:42.000Z", "pattern": "[file:hashes.MD5 = 'f56ae262967ee80ac97edba05cbc2fcf']", "pattern_type": "stix", "pattern_version": "2.1", "valid_from": "2025-03-25T04:55:20Z", "labels": ["#malware", "#Dcrat", "#opendir", "#stealer"], "external_references": [{"source_name": "x.com", "url": "https://x.com/ShanHolo/status/1893595833330700725"}]}, {"type": "indicator", "spec_version": "2.1", "id": "indicator--d13099f5-d075-5a1e-9544-4fba75578f84", "created_by_ref": "identity--ed79cf52-2991-5d8e-b7eb-5bc9d3577885", "created": "2025-02-23T09:36:42.000Z", "modified": "2025-02-23T09:36:42.000Z", "pattern": "[file:hashes.MD5 = '3954800dc5938b12e0df84728a831de3']", "pattern_type": "stix", "pattern_version": "2.1", "valid_from": "2025-03-25T04:55:20Z", "labels": ["#malware", "#Dcrat", "#opendir", "#stealer"], "external_references": [{"source_name": "x.com", "url": "https://x.com/ShanHolo/status/1893595833330700725"}]}, {"type": "indicator", "spec_version": "2.1", "id": "indicator--be6540e7-c4ca-505c-82b4-404d1e3e6786", "created_by_ref": "identity--ea20bd24-c963-5a3e-924d-fca9740f3c87", "created": "2025-02-23T18:46:08.000Z", "modified": "2025-02-23T18:46:08.000Z", "pattern": "[file:hashes.MD5 = 'a18d08d5e585e7673a89a752326b8982']", "pattern_type": "stix", "pattern_version": "2.1", "valid_from": "2025-03-25T04:55:20Z", "external_references": [{"source_name": "x.com", "url": "https://x.com/sicehice/status/1893734102752166035"}]}, {"type": "indicator", "spec_version": "2.1", "id": "indicator--3b6c19b4-1f8f-5b7a-abce-43c1f987d5f6", "created_by_ref": "identity--ea20bd24-c963-5a3e-924d-fca9740f3c87", "created": "2025-02-23T19:15:52.000Z", "modified": "2025-02-23T19:15:52.000Z", "pattern": "[file:hashes.MD5 = '3aad40bf92b14e06ce40fde487e97fe5']", "pattern_type": "stix", "pattern_version": "2.1", "valid_from": "2025-03-25T04:55:20Z", "labels": ["#CobaltStrike", "#opendir"], "external_references": [{"source_name": "x.com", "url": "https://x.com/sicehice/status/1893741584207798300"}]}, {"type": "indicator", "spec_version": "2.1", "id": "indicator--79b2b869-0124-5484-ab05-edb57c23fcc5", "created_by_ref": "identity--ea20bd24-c963-5a3e-924d-fca9740f3c87", "created": "2025-02-23T19:15:52.000Z", "modified": "2025-02-23T19:15:52.000Z", "pattern": "[file:hashes.MD5 = 'fa54b6377e98fc11e04fa2c294604ef2']", "pattern_type": "stix", "pattern_version": "2.1", "valid_from": "2025-03-25T04:55:20Z", "labels": ["#CobaltStrike", "#opendir"], "external_references": [{"source_name": "x.com", "url": "https://x.com/sicehice/status/1893741584207798300"}]}, {"type": "indicator", "spec_version": "2.1", "id": "indicator--089c96dd-d48f-5208-a368-3449e8e70d74", "created_by_ref": "identity--ea20bd24-c963-5a3e-924d-fca9740f3c87", "created": "2025-02-23T19:15:52.000Z", "modified": "2025-02-23T19:15:52.000Z", "pattern": "[file:hashes.MD5 = '49a571dea62ce5ae6f32914150b1294c']", "pattern_type": "stix", "pattern_version": "2.1", "valid_from": "2025-03-25T04:55:20Z", "labels": ["#CobaltStrike", "#opendir"], "external_references": [{"source_name": "x.com", "url": "https://x.com/sicehice/status/1893741584207798300"}]}, {"type": "indicator", "spec_version": "2.1", "id": "indicator--e4d3735a-9378-538f-9a18-5b1b3ef90f91", "created_by_ref": "identity--8a7caf0c-f1e7-5c5c-8a42-836079f9e47b", "created": "2025-02-24T06:38:36.000Z", "modified": "2025-02-24T06:38:36.000Z", "pattern": "[file:hashes.MD5 = 'f733802259ccab5cd386ff4853e64d06']", "pattern_type": "stix", "pattern_version": "2.1", "valid_from": "2025-03-25T04:55:20Z", "labels": ["#stealer"], "external_references": [{"source_name": "x.com", "url": "https://x.com/suyog41/status/1893913400737980735"}]}, {"type": "indicator", "spec_version": "2.1", "id": "indicator--3ed7f159-3999-5697-9fdc-0b53bdf1d6a6", "created_by_ref": "identity--88e1b21a-7b5c-5691-a6da-df79257e75c8", "created": "2025-02-24T14:02:34.000Z", "modified": "2025-02-24T14:02:34.000Z", "pattern": "[file:hashes.MD5 = '17166ab86116b21d6dfa7b83609e118f']", "pattern_type": "stix", "pattern_version": "2.1", "valid_from": "2025-03-25T04:55:20Z", "labels": ["#ransomware"], "external_references": [{"source_name": "x.com", "url": "https://x.com/PaduckLee/status/1894025128129994933"}]}, {"type": "indicator", "spec_version": "2.1", "id": "indicator--98d96bd2-af6b-515f-afa1-6be2897e4aeb", "created_by_ref": "identity--ea20bd24-c963-5a3e-924d-fca9740f3c87", "created": "2025-02-24T23:32:08.000Z", "modified": "2025-02-24T23:32:08.000Z", "pattern": "[file:hashes.MD5 = 'b056caaec12f8b08d1abfd97aee90817']", "pattern_type": "stix", "pattern_version": "2.1", "valid_from": "2025-03-25T04:55:20Z", "labels": ["#opendir"], "external_references": [{"source_name": "x.com", "url": "https://x.com/sicehice/status/1894168466405437492"}]}, {"type": "indicator", "spec_version": "2.1", "id": "indicator--f0b3d6d9-260f-5691-bca8-1f7e20d12ef1", "created_by_ref": "identity--c2d9f1ff-0792-5fce-9fd5-7b5e45ec5e5d", "created": "2025-02-25T02:15:44.000Z", "modified": "2025-02-25T02:15:44.000Z", "pattern": "[file:hashes.MD5 = '18c24843ff17ab866872a720f0ea7043']", "pattern_type": "stix", "pattern_version": "2.1", "valid_from": "2025-03-25T04:55:20Z", "labels": ["#Android", "#malware", "#Trojan"], "external_references": [{"source_name": "x.com", "url": "https://x.com/ReBensk/status/1894209636045119771"}]}, {"type": "indicator", "spec_version": "2.1", "id": "indicator--6182928e-b1b3-5b29-8e91-58c666e6b92b", "created_by_ref": "identity--c2d9f1ff-0792-5fce-9fd5-7b5e45ec5e5d", "created": "2025-02-25T02:27:51.000Z", "modified": "2025-02-25T02:27:51.000Z", "pattern": "[file:hashes.MD5 = '4d8ab3e3dcd3fb01cd4686193ab3e348']", "pattern_type": "stix", "pattern_version": "2.1", "valid_from": "2025-03-25T04:55:20Z", "labels": ["#Android", "#malware", "#Trojan"], "external_references": [{"source_name": "x.com", "url": "https://x.com/ReBensk/status/1894212686251987027"}]}, {"type": "indicator", "spec_version": "2.1", "id": "indicator--37d08ec6-2060-5268-a115-99dbce081ac0", "created_by_ref": "identity--c2d9f1ff-0792-5fce-9fd5-7b5e45ec5e5d", "created": "2025-02-25T06:16:30.000Z", "modified": "2025-02-25T06:16:30.000Z", "pattern": "[file:hashes.MD5 = 'b1de1b929bbdc5b848c620fabb34de8f']", "pattern_type": "stix", "pattern_version": "2.1", "valid_from": "2025-03-25T04:55:20Z", "labels": ["#malware", "#Android", "#Trojan"], "external_references": [{"source_name": "x.com", "url": "https://x.com/ReBensk/status/1894270225203237168"}]}, {"type": "indicator", "spec_version": "2.1", "id": "indicator--a8aae523-b428-5507-ba4d-0924b7de0a83", "created_by_ref": "identity--8a7caf0c-f1e7-5c5c-8a42-836079f9e47b", "created": "2025-02-25T07:33:51.000Z", "modified": "2025-02-25T07:33:51.000Z", "pattern": "[file:hashes.MD5 = 'fcb57db12a4dbdf5a14683a187490c2e']", "pattern_type": "stix", "pattern_version": "2.1", "valid_from": "2025-03-25T04:55:20Z", "labels": ["#stealer"], "external_references": [{"source_name": "x.com", "url": "https://x.com/suyog41/status/1894289692780368173"}]}, {"type": "indicator", "spec_version": "2.1", "id": "indicator--7c610196-febc-509b-ba27-e87c400f738b", "created_by_ref": "identity--8a7caf0c-f1e7-5c5c-8a42-836079f9e47b", "created": "2025-02-25T07:37:56.000Z", "modified": "2025-02-25T07:37:56.000Z", "pattern": "[file:hashes.MD5 = '716a117faa09cd17518fe08bb8dc1f18']", "pattern_type": "stix", "pattern_version": "2.1", "valid_from": "2025-03-25T04:55:20Z", "external_references": [{"source_name": "x.com", "url": "https://x.com/suyog41/status/1894290720627855710"}]}, {"type": "indicator", "spec_version": "2.1", "id": "indicator--df6b6067-dc21-5883-82ee-d49834414c34", "created_by_ref": "identity--8a7caf0c-f1e7-5c5c-8a42-836079f9e47b", "created": "2025-02-25T10:36:02.000Z", "modified": "2025-02-25T10:36:02.000Z", "pattern": "[file:hashes.MD5 = '7a08ca63e6620b690b394163c73a2218']", "pattern_type": "stix", "pattern_version": "2.1", "valid_from": "2025-03-25T04:55:20Z", "labels": ["#stealer"], "external_references": [{"source_name": "x.com", "url": "https://x.com/suyog41/status/1894335541786894759"}]}, {"type": "indicator", "spec_version": "2.1", "id": "indicator--2914192a-d6b0-5e6b-a416-66521df72cdb", "created_by_ref": "identity--8a7caf0c-f1e7-5c5c-8a42-836079f9e47b", "created": "2025-02-25T10:58:28.000Z", "modified": "2025-02-25T10:58:28.000Z", "pattern": "[file:hashes.MD5 = 'dc7c0893f60f87006e10a40f1aec5720']", "pattern_type": "stix", "pattern_version": "2.1", "valid_from": "2025-03-25T04:55:20Z", "labels": ["#stealer"], "external_references": [{"source_name": "x.com", "url": "https://x.com/suyog41/status/1894341186598703191"}]}, {"type": "indicator", "spec_version": "2.1", "id": "indicator--fa140eaa-9b83-538e-8d1b-30bf17de73d0", "created_by_ref": "identity--8a7caf0c-f1e7-5c5c-8a42-836079f9e47b", "created": "2025-02-25T10:58:28.000Z", "modified": "2025-02-25T10:58:28.000Z", "pattern": "[file:hashes.MD5 = '42cbfbc86c27376ded8c03052cbad12a']", "pattern_type": "stix", "pattern_version": "2.1", "valid_from": "2025-03-25T04:55:20Z", "labels": ["#stealer"], "external_references": [{"source_name": "x.com", "url": "https://x.com/suyog41/status/1894341186598703191"}]}, {"type": "indicator", "spec_version": "2.1", "id": "indicator--fc9ed692-93fe-54ea-b32c-467bfe1acd61", "created_by_ref": "identity--fe3e9919-5ccc-5219-855b-0fb8de9ece65", "created": "2025-02-25T12:27:46.000Z", "modified": "2025-02-25T12:27:46.000Z", "pattern": "[file:hashes.MD5 = '75c37d4f76181cd10e38d9a5f9447f50']", "pattern_type": "stix", "pattern_version": "2.1", "valid_from": "2025-03-25T04:55:20Z", "labels": ["#malware", "#Xworm"], "external_references": [{"source_name": "x.com", "url": "https://x.com/mallikarjunfp/status/1894363660346429841"}]}, {"type": "indicator", "spec_version": "2.1", "id": "indicator--e84a7f76-28e5-5cc4-84c8-e785a38ae132", "created_by_ref": "identity--ed79cf52-2991-5d8e-b7eb-5bc9d3577885", "created": "2025-02-25T13:23:29.000Z", "modified": "2025-02-25T13:23:29.000Z", "pattern": "[file:hashes.MD5 = '875408fd2d70c74a47d834fa3f106b4a']", "pattern_type": "stix", "pattern_version": "2.1", "valid_from": "2025-03-25T04:55:20Z", "labels": ["#Lumma"], "external_references": [{"source_name": "x.com", "url": "https://x.com/ShanHolo/status/1894377680281243826"}]}, {"type": "indicator", "spec_version": "2.1", "id": "indicator--fee68174-76f9-5587-94fd-0240936cf8e2", "created_by_ref": "identity--ed79cf52-2991-5d8e-b7eb-5bc9d3577885", "created": "2025-02-25T14:45:28.000Z", "modified": "2025-02-25T14:45:28.000Z", "pattern": "[file:hashes.MD5 = '7c1fe4ce85c7d6cf67e4918525d1fcaf']", "pattern_type": "stix", "pattern_version": "2.1", "valid_from": "2025-03-25T04:55:20Z", "labels": ["#malware", "#Remcos", "#opendir"], "external_references": [{"source_name": "x.com", "url": "https://x.com/ShanHolo/status/1894398314063225112"}]}, {"type": "indicator", "spec_version": "2.1", "id": "indicator--69d940eb-2da6-5c7a-adbd-849e873a898d", "created_by_ref": "identity--3680975d-79fc-510a-8b98-750ca020d93e", "created": "2025-02-26T03:22:21.000Z", "modified": "2025-02-26T03:22:21.000Z", "pattern": "[file:hashes.MD5 = 'D6A6F9E981062F25A351198447FF7FF7']", "pattern_type": "stix", "pattern_version": "2.1", "valid_from": "2025-03-25T04:55:20Z", "labels": ["#phishing"], "external_references": [{"source_name": "x.com", "url": "https://x.com/romonlyht/status/1894588787180933202"}]}, {"type": "indicator", "spec_version": "2.1", "id": "indicator--156ddcfb-56c5-5a2c-8c99-3a10e6779249", "created_by_ref": "identity--ea20bd24-c963-5a3e-924d-fca9740f3c87", "created": "2025-02-26T04:03:42.000Z", "modified": "2025-02-26T04:03:42.000Z", "pattern": "[file:hashes.MD5 = 'e7f11aa8a3f8a1d53278ba40c4882da2']", "pattern_type": "stix", "pattern_version": "2.1", "valid_from": "2025-03-25T04:55:20Z", "external_references": [{"source_name": "x.com", "url": "https://x.com/sicehice/status/1894599193194332226"}]}]}
